pyjej/__main__.py
pyjej/groovy/export_plugins.txt
pyjej/selflib.py
pyjej/tasks.py
pyjej-0.1.8.dist-info/METADATA
pyjej-0.1.8.dist-info/WHEEL
pyjej-0.1.8.dist-info/RECORD
