Metadata-Version: 2.1
Name: pyjej
Version: 0.1.8
Summary: Проект для взаимодействия с Jenkins через CLI
Author: Кустов Денис
Author-email: kudv@pkzdrav.ru
Requires-Python: >=3.8,<4.0
Classifier: Programming Language :: Python :: 3
Classifier: Programming Language :: Python :: 3.8
Classifier: Programming Language :: Python :: 3.9
Classifier: Programming Language :: Python :: 3.10
Classifier: Programming Language :: Python :: 3.11
Requires-Dist: invoke (>=2.1.2,<3.0.0)
Requires-Dist: pyyaml (>=6.0,<7.0)
Requires-Dist: requests (>=2.31.0,<3.0.0)
